[{"marker":[0],"components":[{"x":21,"y":24}]},{"marker":[1],"components":[{"x":17,"y":11}]},{"marker":[2],"components":[{"x":18,"y":11}]},{"marker":[3],"components":[{"x":13,"y":10}]},{"marker":[4],"components":[{"x":22,"y":29}]},{"marker":[5],"components":[{"x":23,"y":31}]},{"marker":[6],"components":[{"x":20,"y":25}]},{"marker":[8],"components":[{"x":20,"y":1}]},{"marker":[9],"components":[{"x":19,"y":3}]},{"marker":[10],"components":[{"x":20,"y":3}]},{"marker":[11],"components":[{"x":22,"y":14}]},{"marker":[12],"components":[{"x":22,"y":13}]},{"marker":[13],"components":[{"x":10,"y":26}]},{"marker":[14],"components":[{"x":9,"y":2}]},{"marker":[15],"components":[{"x":11,"y":8}]},{"marker":[16],"components":[null]}][{"marker":[0],"components":[{"glyph":64,"fg":{"r":1.0,"g":1.0,"b":0.0},"bg":{"r":0.0,"g":0.0,"b":0.0},"render_order":0}]},{"marker":[1],"components":[{"glyph":94,"fg":{"r":1.0,"g":0.0,"b":0.0},"bg":{"r":0.0,"g":0.0,"b":0.0},"render_order":2}]},{"marker":[2],"components":[{"glyph":37,"fg":{"r":0.0,"g":1.0,"b":0.0},"bg":{"r":0.0,"g":0.0,"b":0.0},"render_order":2}]},{"marker":[3],"components":[{"glyph":94,"fg":{"r":1.0,"g":0.0,"b":0.0},"bg":{"r":0.0,"g":0.0,"b":0.0},"render_order":2}]},{"marker":[4],"components":[{"glyph":33,"fg":{"r":1.0,"g":0.0,"b":0.0},"bg":{"r":0.0,"g":0.0,"b":0.0},"render_order":2}]},{"marker":[5],"components":[{"glyph":94,"fg":{"r":1.0,"g":0.0,"b":0.0},"bg":{"r":0.0,"g":0.0,"b":0.0},"render_order":2}]},{"marker":[6],"components":[{"glyph":94,"fg":{"r":1.0,"g":0.0,"b":0.0},"bg":{"r":0.0,"g":0.0,"b":0.0},"render_order":2}]},{"marker":[8],"components":[{"glyph":94,"fg":{"r":1.0,"g":0.0,"b":0.0},"bg":{"r":0.0,"g":0.0,"b":0.0},"render_order":2}]},{"marker":[9],"components":[{"glyph":41,"fg":{"r":1.0,"g":0.64705884,"b":0.0},"bg":{"r":0.0,"g":0.0,"b":0.0},"render_order":2}]},{"marker":[10],"components":[{"glyph":94,"fg":{"r":1.0,"g":0.0,"b":0.0},"bg":{"r":0.0,"g":0.0,"b":0.0},"render_order":2}]},{"marker":[11],"components":[{"glyph":103,"fg":{"r":1.0,"g":0.0,"b":0.0},"bg":{"r":0.0,"g":0.0,"b":0.0},"render_order":1}]},{"marker":[12],"components":[{"glyph":94,"fg":{"r":1.0,"g":0.0,"b":0.0},"bg":{"r":0.0,"g":0.0,"b":0.0},"render_order":2}]},{"marker":[13],"components":[{"glyph":94,"fg":{"r":1.0,"g":0.0,"b":0.0},"bg":{"r":0.0,"g":0.0,"b":0.0},"render_order":2}]},{"marker":[14],"components":[{"glyph":103,"fg":{"r":1.0,"g":0.0,"b":0.0},"bg":{"r":0.0,"g":0.0,"b":0.0},"render_order":1}]},{"marker":[15],"components":[{"glyph":94,"fg":{"r":1.0,"g":0.0,"b":0.0},"bg":{"r":0.0,"g":0.0,"b":0.0},"render_order":2}]},{"marker":[16],"components":[null]}][{"marker":[0],"components":[{}]},{"marker":[1],"components":[null]},{"marker":[2],"components":[null]},{"marker":[3],"components":[null]},{"marker":[4],"components":[null]},{"marker":[5],"components":[null]},{"marker":[6],"components":[null]},{"marker":[8],"components":[null]},{"marker":[9],"components":[null]},{"marker":[10],"components":[null]},{"marker":[11],"components":[null]},{"marker":[12],"components":[null]},{"marker":[13],"components":[null]},{"marker":[14],"components":[null]},{"marker":[15],"components":[null]},{"marker":[16],"components":[null]}][{"marker":[0],"components":[{"visible_tiles":[{"x":24,"y":31},{"x":17,"y":23},{"x":20,"y":32},{"x":16,"y":28},{"x":19,"y":24},{"x":21,"y":24},{"x":22,"y":24},{"x":24,"y":27},{"x":29,"y":25},{"x":17,"y":31},{"x":15,"y":24},{"x":24,"y":24},{"x":15,"y":22},{"x":19,"y":31},{"x":22,"y":23},{"x":23,"y":22},{"x":20,"y":23},{"x":22,"y":27},{"x":16,"y":24},{"x":16,"y":25},{"x":15,"y":26},{"x":16,"y":27},{"x":21,"y":29},{"x":16,"y":26},{"x":23,"y":27},{"x":24,"y":25},{"x":22,"y":29},{"x":17,"y":22},{"x":20,"y":26},{"x":19,"y":28},{"x":20,"y":30},{"x":23,"y":23},{"x":17,"y":28},{"x":27,"y":23},{"x":24,"y":28},{"x":23,"y":31},{"x":19,"y":22},{"x":26,"y":24},{"x":20,"y":25},{"x":20,"y":29},{"x":19,"y":26},{"x":17,"y":25},{"x":19,"y":32},{"x":15,"y":30},{"x":18,"y":31},{"x":22,"y":28},{"x":20,"y":31},{"x":22,"y":22},{"x":18,"y":23},{"x":18,"y":22},{"x":16,"y":22},{"x":17,"y":27},{"x":17,"y":26},{"x":20,"y":24},{"x":20,"y":22},{"x":28,"y":25},{"x":24,"y":26},{"x":26,"y":23},{"x":28,"y":23},{"x":19,"y":29},{"x":25,"y":25},{"x":15,"y":25},{"x":17,"y":30},{"x":23,"y":24},{"x":29,"y":24},{"x":22,"y":30},{"x":21,"y":27},{"x":18,"y":24},{"x":25,"y":24},{"x":22,"y":32},{"x":24,"y":32},{"x":22,"y":26},{"x":23,"y":30},{"x":25,"y":23},{"x":26,"y":25},{"x":19,"y":23},{"x":15,"y":27},{"x":21,"y":31},{"x":20,"y":28},{"x":28,"y":24},{"x":18,"y":29},{"x":18,"y":21},{"x":18,"y":28},{"x":22,"y":31},{"x":27,"y":25},{"x":23,"y":28},{"x":18,"y":30},{"x":18,"y":27},{"x":16,"y":29},{"x":16,"y":23},{"x":21,"y":26},{"x":18,"y":32},{"x":19,"y":25},{"x":27,"y":24},{"x":24,"y":23},{"x":15,"y":23},{"x":21,"y":30},{"x":16,"y":31},{"x":22,"y":25},{"x":15,"y":28},{"x":19,"y":27},{"x":19,"y":30},{"x":21,"y":23},{"x":23,"y":25},{"x":21,"y":32},{"x":20,"y":27},{"x":23,"y":29},{"x":15,"y":29},{"x":17,"y":29},{"x":17,"y":24},{"x":29,"y":23},{"x":24,"y":22},{"x":21,"y":25},{"x":24,"y":30},{"x":21,"y":22},{"x":24,"y":29},{"x":23,"y":32},{"x":18,"y":26},{"x":21,"y":28},{"x":16,"y":30},{"x":18,"y":25},{"x":23,"y":26}],"range":8,"dirty":false}]},{"marker":[1],"components":[null]},{"marker":[2],"components":[null]},{"marker":[3],"components":[null]},{"marker":[4],"components":[null]},{"marker":[5],"components":[null]},{"marker":[6],"components":[null]},{"marker":[8],"components":[null]},{"marker":[9],"components":[null]},{"marker":[10],"components":[null]},{"marker":[11],"components":[{"visible_tiles":[{"x":29,"y":14},{"x":21,"y":13},{"x":25,"y":17},{"x":23,"y":16},{"x":27,"y":13},{"x":28,"y":12},{"x":24,"y":10},{"x":23,"y":11},{"x":22,"y":18},{"x":27,"y":11},{"x":21,"y":14},{"x":25,"y":10},{"x":24,"y":12},{"x":25,"y":13},{"x":25,"y":18},{"x":21,"y":17},{"x":16,"y":8},{"x":23,"y":13},{"x":27,"y":18},{"x":25,"y":15},{"x":27,"y":14},{"x":22,"y":14},{"x":24,"y":9},{"x":17,"y":9},{"x":29,"y":10},{"x":29,"y":18},{"x":25,"y":9},{"x":27,"y":16},{"x":22,"y":15},{"x":22,"y":10},{"x":28,"y":18},{"x":28,"y":10},{"x":24,"y":15},{"x":21,"y":12},{"x":27,"y":12},{"x":24,"y":13},{"x":22,"y":11},{"x":28,"y":16},{"x":26,"y":11},{"x":21,"y":18},{"x":29,"y":12},{"x":28,"y":15},{"x":29,"y":16},{"x":24,"y":11},{"x":24,"y":17},{"x":21,"y":10},{"x":22,"y":16},{"x":21,"y":11},{"x":25,"y":11},{"x":20,"y":12},{"x":28,"y":11},{"x":26,"y":14},{"x":26,"y":10},{"x":29,"y":13},{"x":24,"y":14},{"x":25,"y":12},{"x":28,"y":17},{"x":26,"y":18},{"x":23,"y":18},{"x":29,"y":11},{"x":26,"y":15},{"x":22,"y":17},{"x":26,"y":16},{"x":24,"y":16},{"x":25,"y":8},{"x":23,"y":15},{"x":26,"y":13},{"x":26,"y":17},{"x":23,"y":14},{"x":21,"y":15},{"x":22,"y":13},{"x":23,"y":17},{"x":22,"y":12},{"x":27,"y":17},{"x":23,"y":10},{"x":19,"y":11},{"x":26,"y":12},{"x":28,"y":13},{"x":24,"y":18},{"x":27,"y":15},{"x":28,"y":14},{"x":29,"y":15},{"x":27,"y":10},{"x":18,"y":10},{"x":23,"y":12},{"x":21,"y":16},{"x":25,"y":14},{"x":29,"y":17},{"x":25,"y":16}],"range":8,"dirty":false}]},{"marker":[12],"components":[null]},{"marker":[13],"components":[null]},{"marker":[14],"components":[{"visible_tiles":[{"x":13,"y":6},{"x":8,"y":6},{"x":10,"y":9},{"x":8,"y":2},{"x":12,"y":8},{"x":11,"y":7},{"x":11,"y":1},{"x":6,"y":4},{"x":7,"y":6},{"x":13,"y":7},{"x":10,"y":3},{"x":6,"y":3},{"x":11,"y":2},{"x":12,"y":10},{"x":8,"y":3},{"x":6,"y":7},{"x":7,"y":8},{"x":8,"y":8},{"x":12,"y":3},{"x":10,"y":6},{"x":10,"y":1},{"x":13,"y":2},{"x":8,"y":1},{"x":10,"y":8},{"x":9,"y":1},{"x":11,"y":9},{"x":7,"y":4},{"x":6,"y":8},{"x":7,"y":9},{"x":9,"y":5},{"x":9,"y":3},{"x":12,"y":7},{"x":8,"y":4},{"x":8,"y":7},{"x":8,"y":5},{"x":12,"y":9},{"x":10,"y":10},{"x":13,"y":5},{"x":13,"y":8},{"x":9,"y":10},{"x":13,"y":1},{"x":7,"y":2},{"x":8,"y":10},{"x":12,"y":4},{"x":9,"y":8},{"x":6,"y":6},{"x":12,"y":6},{"x":7,"y":3},{"x":11,"y":6},{"x":6,"y":9},{"x":9,"y":4},{"x":6,"y":1},{"x":13,"y":3},{"x":9,"y":6},{"x":9,"y":2},{"x":11,"y":4},{"x":9,"y":7},{"x":9,"y":9},{"x":7,"y":7},{"x":13,"y":9},{"x":12,"y":5},{"x":13,"y":4},{"x":10,"y":5},{"x":7,"y":1},{"x":6,"y":2},{"x":10,"y":2},{"x":11,"y":5},{"x":10,"y":4},{"x":11,"y":3},{"x":8,"y":9},{"x":12,"y":2},{"x":10,"y":7},{"x":11,"y":10},{"x":6,"y":5},{"x":11,"y":8},{"x":7,"y":5},{"x":12,"y":1}],"range":8,"dirty":false}]},{"marker":[15],"components":[null]},{"marker":[16],"components":[null]}][{"marker":[0],"components":[null]},{"marker":[1],"components":[null]},{"marker":[2],"components":[null]},{"marker":[3],"components":[null]},{"marker":[4],"components":[null]},{"marker":[5],"components":[null]},{"marker":[6],"components":[null]},{"marker":[8],"components":[null]},{"marker":[9],"components":[null]},{"marker":[10],"components":[null]},{"marker":[11],"components":[{}]},{"marker":[12],"components":[null]},{"marker":[13],"components":[null]},{"marker":[14],"components":[{}]},{"marker":[15],"components":[null]},{"marker":[16],"components":[null]}][{"marker":[0],"components":[{"name":"Player"}]},{"marker":[1],"components":[{"name":"Bear Trap"}]},{"marker":[2],"components":[{"name":"Rations"}]},{"marker":[3],"components":[{"name":"Bear Trap"}]},{"marker":[4],"components":[{"name":"Health Potion"}]},{"marker":[5],"components":[{"name":"Bear Trap"}]},{"marker":[6],"components":[{"name":"Bear Trap"}]},{"marker":[8],"components":[{"name":"Bear Trap"}]},{"marker":[9],"components":[{"name":"Fireball Scroll"}]},{"marker":[10],"components":[{"name":"Bear Trap"}]},{"marker":[11],"components":[{"name":"Goblin"}]},{"marker":[12],"components":[{"name":"Bear Trap"}]},{"marker":[13],"components":[{"name":"Bear Trap"}]},{"marker":[14],"components":[{"name":"Goblin"}]},{"marker":[15],"components":[{"name":"Bear Trap"}]},{"marker":[16],"components":[null]}][{"marker":[0],"components":[null]},{"marker":[1],"components":[null]},{"marker":[2],"components":[null]},{"marker":[3],"components":[null]},{"marker":[4],"components":[null]},{"marker":[5],"components":[null]},{"marker":[6],"components":[null]},{"marker":[8],"components":[null]},{"marker":[9],"components":[null]},{"marker":[10],"components":[null]},{"marker":[11],"components":[{}]},{"marker":[12],"components":[null]},{"marker":[13],"components":[null]},{"marker":[14],"components":[{}]},{"marker":[15],"components":[null]},{"marker":[16],"components":[null]}][{"marker":[0],"components":[{"max_hp":30,"hp":30,"defense":2,"power":5}]},{"marker":[1],"components":[null]},{"marker":[2],"components":[null]},{"marker":[3],"components":[null]},{"marker":[4],"components":[null]},{"marker":[5],"components":[null]},{"marker":[6],"components":[null]},{"marker":[8],"components":[null]},{"marker":[9],"components":[null]},{"marker":[10],"components":[null]},{"marker":[11],"components":[{"max_hp":16,"hp":16,"defense":1,"power":4}]},{"marker":[12],"components":[null]},{"marker":[13],"components":[null]},{"marker":[14],"components":[{"max_hp":16,"hp":16,"defense":1,"power":4}]},{"marker":[15],"components":[null]},{"marker":[16],"components":[null]}][{"marker":[0],"components":[null]},{"marker":[1],"components":[null]},{"marker":[2],"components":[null]},{"marker":[3],"components":[null]},{"marker":[4],"components":[null]},{"marker":[5],"components":[null]},{"marker":[6],"components":[null]},{"marker":[8],"components":[null]},{"marker":[9],"components":[null]},{"marker":[10],"components":[null]},{"marker":[11],"components":[null]},{"marker":[12],"components":[null]},{"marker":[13],"components":[null]},{"marker":[14],"components":[null]},{"marker":[15],"components":[null]},{"marker":[16],"components":[null]}][{"marker":[0],"components":[null]},{"marker":[1],"components":[null]},{"marker":[2],"components":[null]},{"marker":[3],"components":[null]},{"marker":[4],"components":[null]},{"marker":[5],"components":[null]},{"marker":[6],"components":[null]},{"marker":[8],"components":[null]},{"marker":[9],"components":[null]},{"marker":[10],"components":[null]},{"marker":[11],"components":[null]},{"marker":[12],"components":[null]},{"marker":[13],"components":[null]},{"marker":[14],"components":[null]},{"marker":[15],"components":[null]},{"marker":[16],"components":[null]}][{"marker":[0],"components":[null]},{"marker":[1],"components":[null]},{"marker":[2],"components":[{}]},{"marker":[3],"components":[null]},{"marker":[4],"components":[{}]},{"marker":[5],"components":[null]},{"marker":[6],"components":[null]},{"marker":[8],"components":[null]},{"marker":[9],"components":[{}]},{"marker":[10],"components":[null]},{"marker":[11],"components":[null]},{"marker":[12],"components":[null]},{"marker":[13],"components":[null]},{"marker":[14],"components":[null]},{"marker":[15],"components":[null]},{"marker":[16],"components":[null]}][{"marker":[0],"components":[null]},{"marker":[1],"components":[null]},{"marker":[2],"components":[{}]},{"marker":[3],"components":[null]},{"marker":[4],"components":[{}]},{"marker":[5],"components":[null]},{"marker":[6],"components":[null]},{"marker":[8],"components":[null]},{"marker":[9],"components":[{}]},{"marker":[10],"components":[null]},{"marker":[11],"components":[null]},{"marker":[12],"components":[null]},{"marker":[13],"components":[null]},{"marker":[14],"components":[null]},{"marker":[15],"components":[null]},{"marker":[16],"components":[null]}][{"marker":[0],"components":[null]},{"marker":[1],"components":[null]},{"marker":[2],"components":[null]},{"marker":[3],"components":[null]},{"marker":[4],"components":[null]},{"marker":[5],"components":[null]},{"marker":[6],"components":[null]},{"marker":[8],"components":[null]},{"marker":[9],"components":[{"range":6}]},{"marker":[10],"components":[null]},{"marker":[11],"components":[null]},{"marker":[12],"components":[null]},{"marker":[13],"components":[null]},{"marker":[14],"components":[null]},{"marker":[15],"components":[null]},{"marker":[16],"components":[null]}][{"marker":[0],"components":[null]},{"marker":[1],"components":[null]},{"marker":[2],"components":[null]},{"marker":[3],"components":[null]},{"marker":[4],"components":[null]},{"marker":[5],"components":[null]},{"marker":[6],"components":[null]},{"marker":[8],"components":[null]},{"marker":[9],"components":[{"damage":20}]},{"marker":[10],"components":[null]},{"marker":[11],"components":[null]},{"marker":[12],"components":[null]},{"marker":[13],"components":[null]},{"marker":[14],"components":[null]},{"marker":[15],"components":[null]},{"marker":[16],"components":[null]}][{"marker":[0],"components":[null]},{"marker":[1],"components":[null]},{"marker":[2],"components":[null]},{"marker":[3],"components":[null]},{"marker":[4],"components":[null]},{"marker":[5],"components":[null]},{"marker":[6],"components":[null]},{"marker":[8],"components":[null]},{"marker":[9],"components":[{"radius":3}]},{"marker":[10],"components":[null]},{"marker":[11],"components":[null]},{"marker":[12],"components":[null]},{"marker":[13],"components":[null]},{"marker":[14],"components":[null]},{"marker":[15],"components":[null]},{"marker":[16],"components":[null]}][{"marker":[0],"components":[null]},{"marker":[1],"components":[null]},{"marker":[2],"components":[null]},{"marker":[3],"components":[null]},{"marker":[4],"components":[null]},{"marker":[5],"components":[null]},{"marker":[6],"components":[null]},{"marker":[8],"components":[null]},{"marker":[9],"components":[null]},{"marker":[10],"components":[null]},{"marker":[11],"components":[null]},{"marker":[12],"components":[null]},{"marker":[13],"components":[null]},{"marker":[14],"components":[null]},{"marker":[15],"components":[null]},{"marker":[16],"components":[null]}][{"marker":[0],"components":[null]},{"marker":[1],"components":[null]},{"marker":[2],"components":[null]},{"marker":[3],"components":[null]},{"marker":[4],"components":[{"heal_amount":8}]},{"marker":[5],"components":[null]},{"marker":[6],"components":[null]},{"marker":[8],"components":[null]},{"marker":[9],"components":[null]},{"marker":[10],"components":[null]},{"marker":[11],"components":[null]},{"marker":[12],"components":[null]},{"marker":[13],"components":[null]},{"marker":[14],"components":[null]},{"marker":[15],"components":[null]},{"marker":[16],"components":[null]}][{"marker":[0],"components":[null]},{"marker":[1],"components":[null]},{"marker":[2],"components":[null]},{"marker":[3],"components":[null]},{"marker":[4],"components":[null]},{"marker":[5],"components":[null]},{"marker":[6],"components":[null]},{"marker":[8],"components":[null]},{"marker":[9],"components":[null]},{"marker":[10],"components":[null]},{"marker":[11],"components":[null]},{"marker":[12],"components":[null]},{"marker":[13],"components":[null]},{"marker":[14],"components":[null]},{"marker":[15],"components":[null]},{"marker":[16],"components":[null]}][{"marker":[0],"components":[null]},{"marker":[1],"components":[null]},{"marker":[2],"components":[null]},{"marker":[3],"components":[null]},{"marker":[4],"components":[null]},{"marker":[5],"components":[null]},{"marker":[6],"components":[null]},{"marker":[8],"components":[null]},{"marker":[9],"components":[null]},{"marker":[10],"components":[null]},{"marker":[11],"components":[null]},{"marker":[12],"components":[null]},{"marker":[13],"components":[null]},{"marker":[14],"components":[null]},{"marker":[15],"components":[null]},{"marker":[16],"components":[null]}][{"marker":[0],"components":[null]},{"marker":[1],"components":[null]},{"marker":[2],"components":[null]},{"marker":[3],"components":[null]},{"marker":[4],"components":[null]},{"marker":[5],"components":[null]},{"marker":[6],"components":[null]},{"marker":[8],"components":[null]},{"marker":[9],"components":[null]},{"marker":[10],"components":[null]},{"marker":[11],"components":[null]},{"marker":[12],"components":[null]},{"marker":[13],"components":[null]},{"marker":[14],"components":[null]},{"marker":[15],"components":[null]},{"marker":[16],"components":[null]}][{"marker":[0],"components":[{"lastacted":1621962611104,"speed_in_ms":100}]},{"marker":[1],"components":[null]},{"marker":[2],"components":[null]},{"marker":[3],"components":[null]},{"marker":[4],"components":[null]},{"marker":[5],"components":[null]},{"marker":[6],"components":[null]},{"marker":[8],"components":[null]},{"marker":[9],"components":[null]},{"marker":[10],"components":[null]},{"marker":[11],"components":[{"lastacted":0,"speed_in_ms":300}]},{"marker":[12],"components":[null]},{"marker":[13],"components":[null]},{"marker":[14],"components":[{"lastacted":0,"speed_in_ms":300}]},{"marker":[15],"components":[null]},{"marker":[16],"components":[null]}][{"marker":[0],"components":[null]},{"marker":[1],"components":[null]},{"marker":[2],"components":[null]},{"marker":[3],"components":[null]},{"marker":[4],"components":[null]},{"marker":[5],"components":[null]},{"marker":[6],"components":[null]},{"marker":[8],"components":[null]},{"marker":[9],"components":[null]},{"marker":[10],"components":[null]},{"marker":[11],"components":[null]},{"marker":[12],"components":[null]},{"marker":[13],"components":[null]},{"marker":[14],"components":[null]},{"marker":[15],"components":[null]},{"marker":[16],"components":[null]}][{"marker":[0],"components":[null]},{"marker":[1],"components":[null]},{"marker":[2],"components":[null]},{"marker":[3],"components":[null]},{"marker":[4],"components":[null]},{"marker":[5],"components":[null]},{"marker":[6],"components":[null]},{"marker":[8],"components":[null]},{"marker":[9],"components":[null]},{"marker":[10],"components":[null]},{"marker":[11],"components":[null]},{"marker":[12],"components":[null]},{"marker":[13],"components":[null]},{"marker":[14],"components":[null]},{"marker":[15],"components":[null]},{"marker":[16],"components":[{"map":{"tiles":["Wall","Wall","Wall","Wall","Wall","Wall","Wall","Wall","Wall","Wall","Wall","Wall","Wall","Wall","Wall","Wall","Wall","Wall","Wall","Wall","Wall","Wall","Wall","Wall","Wall","Wall","Wall","Wall","Wall","Wall","Wall","Wall","Wall","Wall","Wall","Wall","Wall","Wall","Wall","Wall","Wall","Wall","Wall","Wall","Wall","Wall","Wall","Wall","Wall","Wall","Wall","Wall","Wall","Wall","Wall","Wall","Wall","Wall","Wall","Wall","Wall","Wall","Wall","Wall","Wall","Wall","Wall","Wall","Wall","Wall","Wall","Wall","Wall","Wall","Wall","Wall","Wall","Wall","Floor","Floor","Floor","Floor","Floor","Floor","Wall","Wall","Wall","Wall","Wall","Wall","Wall","Wall","Wall","Wall","Wall","Wall","Wall","Wall","Wall","Wall","Wall","Wall","Wall","Wall","Wall","Wall","Wall","Wall","Wall","Wall","Wall","Wall","Wall","Wall","Wall","Wall","Wall","Wall","Wall","Wall","Wall","Wall","Wall","Wall","Wall","Wall","Wall","Floor","Floor","Floor","Floor","Floor","Floor","Wall","Wall","Wall","Wall","Wall","Floor","Floor","Floor","Floor","Floor","Floor","Wall","Wall","Wall","Wall","Wall","Wall","Wall","Wall","Wall","Wall","Wall","Wall","Wall","Wall","Wall","Wall","Wall","Wall","Wall","Wall","Wall","Wall","Wall","Wall","Wall","Wall","Wall","Wall","Wall","Wall","Wall","Wall","Wall","Wall","Wall","Wall","Wall","Wall","Wall","Wall","Wall","Wall","Wall","Floor","Floor","Floor","Floor","Floor","Floor","Wall","Wall","Wall","Wall","Wall","Floor","Floor","Floor","Floor","Floor","Floor","Floor","Wall","Wall","Wall","Wall","Wall","Wall","Wall","Wall","Wall","Wall","Wall","Wall","Wall","Wall","Wall","Wall","Wall","Wall","Wall","Wall","Wall","Wall","Wall","Wall","Wall","Wall","Wall","Wall","Wall","Wall","Wall","Wall","Wall","Wall","Wall","Wall","Wall","Wall","Wall","Wall","Wall","Wall","Floor","Floor","DownStairs","Floor","Floor","Floor","Wall","Wall","Wall","Wall","Wall","Floor","Floor","Floor","Floor","Floor","Floor","Floor","Wall","Wall","Wall","Wall","Wall","Wall","Wall","Wall","Wall","Wall","Wall","Wall","Wall","Wall","Wall","Wall","Wall","Wall","Wall","Wall","Wall","Wall","Wall","Wall","Wall","Wall","Wall","Wall","Wall","Wall","Wall","Wall","Wall","Wall","Wall","Wall","Wall","Wall","Wall","Wall","Wall","Wall","Floor","Floor","Floor","Floor","Floor","Floor","Wall","Wall","Wall","Wall","Wall","Floor","Floor","Floor","Floor","Floor","Floor","Floor","Wall","Wall","Wall","Wall","Wall","Wall","Wall","Wall","Wall","Wall","Wall","Wall","Wall","Wall","Wall","Wall","Wall","Wall","Wall","Wall","Wall","Wall","Wall","Wall","Wall","Wall","Wall","Wall","Wall","Wall","Wall","Wall","Wall","Wall","Wall","Wall","Wall","Wall","Wall","Wall","Wall","Wall","Floor","Floor","Floor","Floor","Floor","Floor","Wall","Wall","Wall","Wall","Wall","Floor","Floor","Floor","Floor","Floor","Floor","Floor","Wall","Wall","Wall","Wall","Wall","Wall","Wall","Wall","Wall","Wall","Wall","Wall","Wall","Wall","Wall","Wall","Wall","Wall","Wall","Wall","Wall","Floor","Floor","Floor","Floor","Floor","Floor","Floor","Floor","Wall","Wall","Wall","Wall","Wall","Wall","Wall","Wall","Wall","Wall","Wall","Wall","Wall","Floor","Floor","Floor","Floor","Floor","Floor","Wall","Wall","Wall","Wall","Wall","Floor","Floor","Floor","Floor","Floor","Floor","Floor","Wall","Wall","Wall","Wall","Wall","Wall","Wall","Wall","Wall","Wall","Wall","Wall","Wall","Wall","Wall","Wall","Wall","Wall","Wall","Wall","Wall","Floor","Floor","Floor","Floor","Floor","Floor","Floor","Floor","Wall","Wall","Wall","Wall","Wall","Wall","Wall","Wall","Wall","Wall","Wall","Wall","Wall","Floor","Floor","Floor","Floor","Floor","Floor","Wall","Wall","Wall","Wall","Wall","Wall","Floor","Wall","Wall","Wall","Wall","Floor","Wall","Wall","Wall","Wall","Wall","Wall","Wall","Wall","Wall","Wall","Wall","Wall","Wall","Wall","Wall","Wall","Wall","Wall","Wall","Wall","Wall","Floor","Floor","Floor","Floor","Floor","Floor","Floor","Floor","Wall","Wall","Wall","Wall","Wall","Wall","Wall","Wall","Wall","Wall","Wall","Wall","Wall","Wall","Wall","Floor","Floor","Floor","Floor","Floor","Floor","Floor","Floor","Floor","Floor","Floor","Floor","Floor","Floor","Floor","Floor","Floor","Floor","Floor","Floor","Floor","Floor","Floor","Floor","Floor","Floor","Floor","Floor","Floor","Floor","Floor","Floor","Floor","Floor","Floor","Floor","Floor","Floor","Floor","Floor","Floor","Floor","Floor","Floor","Floor","Wall","Wall","Wall","Wall","Wall","Wall","Wall","Wall","Wall","Wall","Wall","Wall","Wall","Wall","Wall","Wall","Wall","Wall","Wall","Floor","Floor","Floor","Floor","Floor","Floor","Floor","Floor","Wall","Wall","Wall","Floor","Wall","Wall","Wall","Wall","Wall","Wall","Wall","Wall","Wall","Wall","Wall","Floor","Floor","Floor","Floor","Floor","Floor","Floor","Floor","Floor","Wall","Floor","Floor","Floor","Floor","Floor","Floor","Floor","Floor","Wall","Wall","Wall","Wall","Wall","Wall","Wall","Wall","Wall","Wall","Wall","Wall","Wall","Wall","Wall","Wall","Wall","Wall","Wall","Floor","Floor","Floor","Floor","Floor","Floor","Floor","Floor","Wall","Floor","Floor","Floor","Floor","Floor","Floor","Floor","Wall","Wall","Wall","Wall","Wall","Wall","Wall","Floor","Floor","Floor","Floor","Floor","Floor","Floor","Floor","Floor","Wall","Floor","Floor","Floor","Floor","Floor","Floor","Floor","Floor","Wall","Wall","Wall","Wall","Wall","Wall","Wall","Wall","Wall","Wall","Wall","Wall","Wall","Wall","Wall","Wall","Wall","Wall","Wall","Floor","Floor","Floor","Floor","Floor","Floor","Floor","Floor","Wall","Floor","Floor","Floor","Floor","Floor","Floor","Floor","Wall","Wall","Wall","Wall","Wall","Wall","Wall","Floor","Floor","Floor","Floor","Floor","Floor","Floor","Floor","Floor","Wall","Floor","Floor","Floor","Floor","Floor","Floor","Floor","Floor","Wall","Wall","Wall","Wall","Wall","Wall","Wall","Wall","Wall","Wall","Wall","Wall","Wall","Wall","Floor","Floor","Floor","Floor","Floor","Floor","Floor","Floor","Floor","Floor","Floor","Floor","Floor","Floor","Floor","Floor","Floor","Floor","Floor","Floor","Floor","Wall","Wall","Wall","Wall","Wall","Wall","Wall","Floor","Floor","Floor","Floor","Floor","Floor","Floor","Floor","Floor","Floor","Floor","Floor","Floor","Floor","Floor","Floor","Floor","Floor","Wall","Wall","Wall","Wall","Wall","Wall","Wall","Wall","Wall","Wall","Wall","Wall","Wall","Wall","Floor","Wall","Wall","Wall","Wall","Floor","Floor","Floor","Floor","Floor","Floor","Floor","Floor","Wall","Floor","Floor","Floor","Floor","Floor","Floor","Floor","Wall","Wall","Wall","Wall","Wall","Wall","Wall","Floor","Floor","Floor","Floor","Floor","Floor","Floor","Floor","Floor","Wall","Floor","Floor","Floor","Floor","Floor","Floor","Floor","Floor","Wall","Wall","Wall","Wall","Wall","Wall","Wall","Wall","Wall","Wall","Wall","Wall","Wall","Wall","Floor","Wall","Wall","Wall","Wall","Floor","Floor","Floor","Floor","Floor","Floor","Floor","Floor","Wall","Floor","Floor","Floor","Floor","Floor","Floor","Floor","Wall","Wall","Wall","Wall","Wall","Wall","Wall","Floor","Floor","Floor","Floor","Floor","Floor","Floor","Floor","Floor","Wall","Wall","Wall","Wall","Floor","Wall","Wall","Wall","Wall","Wall","Wall","Wall","Wall","Wall","Wall","Wall","Wall","Wall","Wall","Wall","Wall","Wall","Wall","Floor","Wall","Wall","Wall","Wall","Floor","Floor","Floor","Floor","Floor","Floor","Floor","Floor","Wall","Floor","Floor","Floor","Floor","Floor","Floor","Floor","Wall","Wall","Wall","Wall","Wall","Wall","Wall","Floor","Floor","Floor","Floor","Floor","Floor","Floor","Floor","Floor","Wall","Wall","Wall","Wall","Floor","Wall","Wall","Wall","Wall","Wall","Wall","Wall","Wall","Wall","Wall","Wall","Wall","Wall","Wall","Wall","Wall","Wall","Wall","Floor","Wall","Wall","Wall","Wall","Wall","Wall","Wall","Floor","Wall","Wall","Floor","Wall","Wall","Floor","Floor","Floor","Floor","Floor","Floor","Floor","Wall","Wall","Wall","Wall","Wall","Wall","Wall","Floor","Floor","Floor","Floor","Floor","Floor","Floor","Floor","Floor","Wall","Wall","Wall","Wall","Floor","Wall","Wall","Wall","Wall","Wall","Wall","Wall","Wall","Wall","Wall","Wall","Wall","Wall","Wall","Wall","Wall","Wall","Wall","Floor","Wall","Wall","Wall","Wall","Wall","Wall","Wall","Floor","Wall","Wall","Floor","Wall","Wall","Wall","Wall","Wall","Wall","Wall","Wall","Wall","Wall","Wall","Wall","Wall","Wall","Wall","Wall","Wall","Wall","Wall","Floor","Wall","Wall","Wall","Wall","Wall","Wall","Wall","Wall","Wall","Floor","Wall","Wall","Wall","Wall","Wall","Wall","Wall","Wall","Wall","Wall","Wall","Wall","Wall","Wall","Wall","Wall","Wall","Wall","Floor","Wall","Wall","Wall","Wall","Wall","Wall","Wall","Floor","Wall","Wall","Floor","Wall","Wall","Wall","Wall","Wall","Wall","Wall","Wall","Wall","Wall","Wall","Wall","Wall","Wall","Wall","Wall","Wall","Wall","Wall","Floor","Wall","Wall","Wall","Wall","Wall","Wall","Wall","Wall","Wall","Floor","Wall","Wall","Wall","Wall","Wall","Wall","Wall","Wall","Wall","Wall","Wall","Wall","Wall","Wall","Wall","Wall","Wall","Wall","Floor","Wall","Wall","Wall","Wall","Wall","Wall","Wall","Floor","Wall","Wall","Floor","Wall","Wall","Wall","Wall","Wall","Wall","Wall","Wall","Wall","Wall","Wall","Wall","Wall","Wall","Wall","Wall","Wall","Wall","Wall","Floor","Wall","Wall","Wall","Wall","Wall","Wall","Wall","Wall","Wall","Floor","Wall","Wall","Wall","Wall","Wall","Wall","Wall","Wall","Wall","Wall","Wall","Wall","Wall","Wall","Wall","Wall","Floor","Floor","Floor","Floor","Floor","Floor","Floor","Wall","Wall","Wall","Floor","Wall","Wall","Floor","Wall","Wall","Wall","Wall","Wall","Wall","Wall","Wall","Wall","Wall","Wall","Wall","Wall","Wall","Wall","Wall","Floor","Floor","Floor","Floor","Floor","Floor","Wall","Wall","Wall","Wall","Wall","Floor","Floor","Floor","Floor","Floor","Floor","Wall","Wall","Wall","Wall","Wall","Wall","Wall","Wall","Wall","Wall","Wall","Wall","Wall","Floor","Floor","Floor","Floor","Floor","Floor","Floor","Wall","Wall","Wall","Floor","Wall","Wall","Floor","Wall","Wall","Wall","Wall","Wall","Wall","Wall","Wall","Wall","Wall","Wall","Wall","Wall","Wall","Wall","Wall","Floor","Floor","Floor","Floor","Floor","Floor","Wall","Wall","Wall","Wall","Wall","Floor","Floor","Floor","Floor","Floor","Floor","Wall","Wall","Wall","Wall","Wall","Wall","Wall","Wall","Wall","Wall","Wall","Wall","Wall","Floor","Floor","Floor","Floor","Floor","Floor","Floor","Wall","Wall","Wall","Floor","Floor","Floor","Floor","Floor","Floor","Floor","Floor","Wall","Wall","Wall","Wall","Wall","Wall","Wall","Wall","Wall","Wall","Wall","Wall","Floor","Floor","Floor","Floor","Floor","Floor","Wall","Wall","Wall","Wall","Wall","Floor","Floor","Floor","Floor","Floor","Floor","Wall","Wall","Wall","Wall","Wall","Wall","Wall","Wall","Wall","Wall","Wall","Wall","Wall","Floor","Floor","Floor","Floor","Floor","Floor","Floor","Wall","Wall","Wall","Floor","Floor","Floor","Floor","Floor","Floor","Floor","Floor","Floor","Floor","Floor","Floor","Floor","Floor","Floor","Floor","Floor","Floor","Floor","Floor","Floor","Floor","Floor","Floor","Floor","Floor","Wall","Wall","Wall","Wall","Wall","Floor","Floor","Floor","Floor","Floor","Floor","Wall","Wall","Wall","Wall","Wall","Wall","Wall","Wall","Wall","Wall","Wall","Wall","Wall","Floor","Floor","Floor","Floor","Floor","Floor","Floor","Wall","Wall","Wall","Floor","Floor","Floor","Floor","Floor","Floor","Floor","Floor","Wall","Wall","Wall","Wall","Wall","Wall","Wall","Wall","Wall","Wall","Wall","Wall","Floor","Floor","Floor","Floor","Floor","Floor","Wall","Wall","Wall","Wall","Wall","Floor","Floor","Floor","Floor","Floor","Floor","Wall","Wall","Wall","Wall","Wall","Wall","Wall","Wall","Wall","Wall","Wall","Wall","Wall","Floor","Floor","Floor","Floor","Floor","Floor","Floor","Wall","Wall","Wall","Floor","Floor","Floor","Floor","Floor","Floor","Floor","Floor","Wall","Wall","Wall","Wall","Wall","Wall","Wall","Wall","Wall","Wall","Wall","Wall","Floor","Floor","Floor","Floor","Floor","Floor","Wall","Wall","Wall","Wall","Wall","Floor","Floor","Floor","Floor","Floor","Floor","Wall","Wall","Wall","Wall","Wall","Wall","Wall","Wall","Wall","Wall","Wall","Wall","Wall","Floor","Floor","Floor","Floor","Floor","Floor","Floor","Wall","Wall","Wall","Floor","Floor","Floor","Floor","Floor","Floor","Floor","Floor","Wall","Wall","Wall","Wall","Wall","Wall","Wall","Wall","Wall","Wall","Wall","Wall","Floor","Floor","Floor","Floor","Floor","Floor","Wall","Wall","Wall","Wall","Wall","Floor","Floor","Floor","Floor","Floor","Floor","Wall","Wall","Wall","Wall","Wall","Wall","Wall","Wall","Wall","Wall","Wall","Wall","Wall","Floor","Floor","Floor","Floor","Floor","Floor","Floor","Wall","Wall","Wall","Floor","Floor","Floor","Floor","Floor","Floor","Floor","Floor","Wall","Wall","Wall","Wall","Wall","Wall","Wall","Wall","Wall","Wall","Wall","Wall","Floor","Floor","Floor","Floor","Floor","Floor","Wall","Wall","Wall","Wall","Wall","Floor","Floor","Floor","Floor","Floor","Floor","Wall","Wall","Wall","Wall","Wall","Wall","Wall","Wall","Wall","Wall","Wall","Wall","Wall","Wall","Wall","Floor","Wall","Wall","Wall","Wall","Wall","Wall","Wall","Floor","Floor","Floor","Floor","Floor","Floor","Floor","Floor","Wall","Wall","Wall","Wall","Wall","Wall","Wall","Wall","Wall","Wall","Wall","Wall","Wall","Wall","Wall","Floor","Wall","Wall","Wall","Wall","Wall","Wall","Wall","Floor","Floor","Floor","Floor","Floor","Floor","Wall","Wall","Wall","Wall","Wall","Wall","Wall","Wall","Wall","Wall","Wall","Wall","Wall","Floor","Floor","Floor","Floor","Floor","Floor","Floor","Wall","Wall","Wall","Floor","Floor","Floor","Floor","Floor","Floor","Floor","Floor","Wall","Wall","Wall","Floor","Floor","Floor","Floor","Floor","Floor","Floor","Floor","Wall","Wall","Wall","Wall","Floor","Wall","Wall","Wall","Wall","Wall","Wall","Wall","Wall","Wall","Floor","Wall","Wall","Wall","Wall","Wall","Wall","Wall","Wall","Wall","Wall","Wall","Wall","Wall","Wall","Wall","Wall","Floor","Floor","Floor","Floor","Floor","Floor","Floor","Wall","Wall","Wall","Floor","Floor","Floor","Floor","Floor","Floor","Floor","Floor","Wall","Wall","Wall","Floor","Floor","Floor","Floor","Floor","Floor","Floor","Floor","Wall","Wall","Wall","Wall","Floor","Wall","Wall","Wall","Wall","Wall","Wall","Wall","Wall","Wall","Floor","Wall","Wall","Wall","Wall","Wall","Wall","Wall","Wall","Wall","Wall","Wall","Wall","Wall","Wall","Wall","Wall","Floor","Floor","Floor","Floor","Floor","Floor","Floor","Wall","Wall","Wall","Floor","Wall","Wall","Wall","Wall","Wall","Wall","Wall","Wall","Wall","Wall","Floor","Floor","Floor","Floor","Floor","Floor","Floor","Floor","Wall","Wall","Wall","Wall","Floor","Wall","Wall","Wall","Wall","Wall","Wall","Wall","Wall","Wall","Floor","Wall","Wall","Wall","Wall","Wall","Wall","Wall","Wall","Wall","Wall","Wall","Wall","Wall","Wall","Wall","Wall","Floor","Floor","Floor","Floor","Floor","Floor","Floor","Floor","Floor","Floor","Floor","Floor","Floor","Floor","Floor","Floor","Floor","Floor","Floor","Floor","Floor","Floor","Floor","Floor","Floor","Floor","Floor","Floor","Floor","Floor","Floor","Floor","Floor","Floor","Floor","Floor","Floor","Floor","Floor","Floor","Floor","Floor","Floor","Floor","Wall","Wall","Wall","Wall","Wall","Wall","Wall","Wall","Wall","Wall","Wall","Wall","Wall","Wall","Wall","Wall","Floor","Floor","Floor","Floor","Floor","Floor","Floor","Wall","Wall","Wall","Wall","Wall","Wall","Wall","Wall","Wall","Wall","Wall","Wall","Wall","Wall","Floor","Floor","Floor","Floor","Floor","Floor","Floor","Floor","Wall","Wall","Wall","Wall","Wall","Wall","Wall","Wall","Wall","Wall","Wall","Wall","Wall","Wall","Wall","Wall","Wall","Wall","Wall","Wall","Wall","Wall","Wall","Wall","Wall","Wall","Wall","Wall","Wall","Wall","Wall","Floor","Floor","Floor","Floor","Floor","Floor","Floor","Wall","Wall","Wall","Wall","Wall","Wall","Wall","Wall","Wall","Wall","Wall","Wall","Wall","Wall","Floor","Floor","Floor","Floor","Floor","Floor","Floor","Floor","Wall","Wall","Wall","Wall","Wall","Wall","Wall","Wall","Wall","Wall","Wall","Wall","Wall","Wall","Wall","Wall","Wall","Wall","Wall","Wall","Wall","Wall","Wall","Wall","Wall","Wall","Wall","Wall","Wall","Wall","Wall","Floor","Floor","Floor","Floor","Floor","Floor","Floor","Wall","Wall","Wall","Wall","Wall","Wall","Wall","Wall","Wall","Wall","Wall","Wall","Wall","Wall","Floor","Floor","Floor","Floor","Floor","Floor","Floor","Floor","Wall","Wall","Wall","Wall","Wall","Wall","Wall","Wall","Wall","Wall","Wall","Wall","Wall","Wall","Wall","Wall","Wall","Wall","Wall","Wall","Wall","Wall","Wall","Wall","Wall","Wall","Wall","Wall","Wall","Wall","Wall","Floor","Floor","Floor","Floor","Floor","Floor","Floor","Wall","Wall","Wall","Wall","Wall","Wall","Wall","Wall","Wall","Wall","Wall","Wall","Wall","Wall","Floor","Floor","Floor","Floor","Floor","Floor","Floor","Floor","Wall","Wall","Wall","Wall","Wall","Wall","Wall","Wall","Wall","Wall","Wall","Wall","Wall","Wall","Wall","Wall","Wall","Wall","Wall","Wall","Wall","Wall","Wall","Wall","Wall","Wall","Wall","Wall","Wall","Wall","Wall","Wall","Wall","Wall","Wall","Wall","Wall","Wall","Wall","Wall","Wall","Wall","Wall","Wall","Wall","Wall","Wall","Wall","Wall","Wall","Wall","Wall","Wall","Wall","Wall","Wall","Wall","Wall","Wall","Wall","Wall","Wall","Wall","Wall","Wall","Wall","Wall","Wall","Wall","Wall","Wall","Wall","Wall","Wall","Wall","Wall","Wall","Wall","Wall","Wall","Wall","Wall","Wall","Wall","Wall","Wall","Wall","Wall","Wall","Wall","Wall","Wall","Wall","Wall","Wall","Wall","Wall","Wall","Wall","Wall","Wall","Wall","Wall","Wall","Wall","Wall","Wall","Wall","Wall","Wall","Wall","Wall","Wall","Wall","Wall","Wall","Wall","Wall","Wall","Wall","Wall","Wall","Wall","Wall","Wall","Wall","Wall","Wall","Wall","Wall","Wall","Wall","Wall","Wall","Wall","Wall","Wall","Wall","Wall","Wall","Wall","Wall","Wall","Wall","Wall","Wall","Wall","Wall","Wall","Wall","Wall","Wall","Wall","Wall","Wall","Wall","Wall","Wall","Wall","Wall","Wall","Wall","Wall","Wall","Wall","Wall","Wall","Wall","Wall","Wall","Wall","Wall","Wall","Wall","Wall","Wall","Wall","Wall","Wall","Wall","Wall","Wall","Wall","Wall","Wall","Wall","Wall","Wall","Wall","Wall","Wall","Wall","Wall","Wall","Wall","Wall","Wall","Wall","Wall","Wall","Wall","Wall","Wall","Wall","Wall","Wall","Wall","Wall","Wall","Wall","Wall","Wall","Wall","Wall","Wall","Wall","Wall","Wall","Wall","Wall","Wall","Wall","Wall","Wall","Wall","Wall","Wall","Wall","Wall","Wall","Wall","Wall","Wall","Wall","Wall","Wall","Wall","Wall","Wall","Wall","Wall","Wall","Wall","Wall","Wall","Wall","Wall","Wall","Wall","Wall","Wall","Wall","Wall","Wall","Wall","Wall","Wall","Wall","Wall","Wall","Wall","Wall","Wall","Wall","Wall","Wall","Wall","Wall","Wall","Wall","Wall","Wall","Wall","Wall","Wall","Wall","Wall","Wall","Wall","Wall","Wall","Wall","Wall","Wall","Wall","Wall","Wall","Wall","Wall","Wall","Wall","Wall","Wall","Wall","Wall","Wall","Wall","Wall","Wall","Wall","Wall","Wall","Wall","Wall","Wall","Wall","Wall","Wall","Wall","Wall","Wall","Wall","Wall","Wall","Wall","Wall","Wall","Wall","Wall","Wall","Wall","Wall","Wall","Wall","Wall"],"rooms":[{"x1":46,"x2":52,"y1":20,"y2":29},{"x1":35,"x2":44,"y1":9,"y2":17},{"x1":26,"x2":34,"y1":29,"y2":37},{"x1":12,"x2":20,"y1":9,"y2":16},{"x1":35,"x2":41,"y1":20,"y2":28},{"x1":16,"x2":23,"y1":22,"y2":31},{"x1":17,"x2":23,"y1":0,"y2":7},{"x1":21,"x2":28,"y1":10,"y2":17},{"x1":5,"x2":12,"y1":20,"y2":28},{"x1":5,"x2":12,"y1":29,"y2":37},{"x1":45,"x2":53,"y1":5,"y2":14},{"x1":6,"x2":12,"y1":1,"y2":8}],"width":60,"height":43,"revealed_tiles":[false,false,false,false,false,false,false,false,false,false,false,false,false,false,false,false,false,false,false,false,false,false,false,false,false,false,false,false,false,false,false,false,false,false,false,false,false,false,false,false,false,false,false,false,false,false,false,false,false,false,false,false,false,false,false,false,false,false,false,false,false,false,false,false,false,false,false,false,false,false,false,false,false,false,false,false,false,false,false,false,false,false,false,false,false,false,false,false,false,false,false,false,false,false,false,false,false,false,false,false,false,false,false,false,false,false,false,false,false,false,false,false,false,false,false,false,false,false,false,false,false,false,false,false,false,false,false,false,false,false,false,false,false,false,false,false,false,false,false,false,false,false,false,false,false,false,false,false,false,false,false,false,false,false,false,false,false,false,false,false,false,false,false,false,false,false,false,false,false,false,false,false,false,false,false,false,false,false,false,false,false,false,false,false,false,false,false,false,false,false,false,false,false,false,false,false,false,false,false,false,false,false,false,false,false,false,false,false,false,false,false,false,false,false,false,false,false,false,false,false,false,false,false,false,false,false,false,false,false,false,false,false,false,false,false,false,false,false,false,false,false,false,false,false,false,false,false,false,false,false,false,false,false,false,false,false,false,false,false,false,false,false,false,false,false,false,false,false,false,false,false,false,false,false,false,false,false,false,false,false,false,false,false,false,false,false,false,false,false,false,false,false,false,false,false,false,false,false,false,false,false,false,false,false,false,false,false,false,false,false,false,false,false,false,false,false,false,false,false,false,false,false,false,false,false,false,false,false,false,false,false,false,false,false,false,false,false,false,false,false,false,false,false,false,false,true,true,true,true,true,true,true,true,false,false,false,false,false,false,false,false,false,false,false,false,false,false,false,false,false,false,false,false,false,false,false,false,false,false,false,false,false,false,false,false,false,false,false,false,false,false,false,false,false,false,false,false,false,false,false,false,false,false,false,false,true,true,true,true,true,true,true,true,true,true,false,false,false,false,false,false,false,false,false,false,false,false,false,false,false,false,false,false,false,false,false,false,false,false,false,false,false,false,false,false,false,false,false,false,false,false,false,false,false,false,false,false,false,false,false,false,false,false,false,false,true,true,true,true,true,true,true,true,true,true,false,false,false,false,false,false,false,false,false,false,false,false,false,false,false,false,false,false,false,false,false,false,false,false,false,false,false,false,false,false,false,false,false,false,false,false,false,false,false,false,false,true,true,true,true,true,true,true,true,true,true,true,true,true,true,true,true,true,true,true,false,false,false,false,false,false,false,false,false,false,false,false,false,false,false,false,false,false,false,false,false,false,false,false,false,false,false,false,false,false,false,false,false,false,false,false,false,false,false,false,true,true,true,true,true,true,true,true,true,true,true,true,true,true,true,true,true,true,true,true,false,false,false,false,false,false,false,false,false,false,false,false,false,false,false,false,false,false,false,false,false,false,false,false,false,false,false,false,false,false,false,false,false,false,false,false,false,false,false,false,true,true,true,true,true,true,true,true,true,true,true,true,true,true,true,true,true,true,true,true,false,false,false,false,false,false,false,false,false,false,false,false,false,false,false,false,false,false,false,false,false,false,false,false,false,false,false,false,false,false,false,false,false,false,false,false,false,false,false,false,true,true,true,true,true,true,true,true,true,true,true,true,true,true,true,true,true,true,true,true,false,false,false,false,false,false,false,false,false,false,false,false,false,false,false,false,false,false,false,false,false,false,false,false,false,false,false,false,false,false,false,false,false,false,false,false,false,false,false,false,true,true,true,true,true,true,true,true,true,true,true,true,true,true,true,true,true,true,true,true,false,false,false,false,false,false,false,false,false,false,false,false,false,false,false,false,false,false,false,false,false,false,false,false,false,false,false,false,false,false,false,false,false,false,false,false,false,false,false,false,true,true,true,true,true,true,true,true,true,true,true,true,true,true,true,true,true,true,true,true,false,false,false,false,false,false,false,false,false,false,false,false,false,false,false,false,false,false,false,false,false,false,false,false,false,false,false,false,false,false,false,false,false,false,false,false,false,false,false,false,true,true,true,true,true,true,true,true,true,true,true,true,true,true,true,true,true,true,true,true,false,false,false,false,false,false,false,false,false,false,false,false,false,false,false,false,false,false,false,false,false,false,false,false,false,false,false,false,false,false,false,false,false,false,false,false,false,false,false,false,true,true,true,true,true,true,true,true,true,true,true,true,true,true,true,true,true,true,true,true,false,false,false,false,false,false,false,false,false,false,false,false,false,false,false,false,false,false,false,false,false,false,false,false,false,false,false,false,false,false,false,false,false,false,false,false,false,false,false,false,true,true,true,true,true,true,true,true,true,true,true,false,false,true,true,true,false,false,false,false,false,false,false,false,false,false,false,false,false,false,false,false,false,false,false,false,false,false,false,false,false,false,false,false,false,false,false,false,false,false,false,false,false,false,false,false,false,false,false,false,true,true,true,true,true,true,true,true,true,true,true,false,false,true,true,true,false,false,false,false,false,false,false,false,false,false,false,false,false,false,false,false,false,false,false,false,false,false,false,false,false,false,false,false,false,false,false,false,false,false,false,false,false,false,false,false,false,false,false,false,true,true,true,true,true,true,true,true,true,true,true,false,false,true,true,true,false,false,false,false,false,false,false,false,false,false,false,false,false,false,false,false,false,false,false,false,false,false,false,false,false,false,false,false,false,false,false,false,false,false,false,false,false,false,false,false,false,false,false,false,false,false,false,true,true,true,false,false,false,false,false,false,false,true,true,true,false,false,false,false,false,false,false,false,false,false,false,false,false,false,false,false,false,false,false,false,false,false,false,false,false,false,false,false,false,false,false,false,false,false,false,false,false,false,false,false,false,false,false,false,true,true,true,true,true,true,true,true,false,false,false,true,true,true,true,true,true,true,true,false,false,false,false,false,false,false,false,false,false,false,false,false,false,false,false,false,false,false,false,false,false,false,false,true,false,false,false,false,false,false,false,false,false,false,false,false,false,false,false,false,true,true,true,true,true,true,true,true,false,false,false,true,true,true,true,true,true,true,true,false,false,false,false,false,false,false,false,false,false,false,false,false,false,false,false,false,false,false,false,false,true,true,true,true,true,true,true,true,true,true,false,false,false,false,false,false,false,false,false,false,true,true,true,true,true,true,true,true,false,false,false,true,true,true,true,true,true,true,true,false,false,false,false,false,false,false,false,false,false,false,false,false,false,false,false,false,false,false,false,false,true,true,true,true,true,true,true,true,true,true,true,true,true,true,true,true,true,true,true,true,true,true,true,true,true,true,true,true,false,false,false,true,true,true,true,true,true,true,true,false,false,false,false,false,false,false,false,false,false,false,false,false,false,false,false,false,false,false,false,false,true,true,true,true,true,true,true,true,true,true,true,true,true,true,true,true,true,true,true,true,true,true,true,true,true,true,true,true,false,false,false,true,true,true,true,true,true,true,true,false,false,false,false,false,false,false,false,false,false,false,false,false,false,false,false,false,false,false,false,false,true,true,true,true,true,true,true,true,true,true,true,true,true,true,true,true,true,true,true,true,true,true,true,true,true,true,true,true,false,false,false,true,true,true,true,true,true,true,true,false,false,false,false,false,false,false,false,false,false,false,false,false,false,false,false,false,false,false,false,false,true,true,true,true,true,true,true,true,true,true,false,false,false,false,false,false,false,false,false,false,true,true,true,true,true,true,true,true,false,false,false,true,true,true,true,true,true,true,true,false,false,false,false,false,false,false,false,false,false,false,false,false,false,false,false,false,false,false,false,false,true,true,true,true,true,true,true,true,true,true,false,false,false,false,false,false,false,false,false,false,true,true,true,true,true,true,true,true,false,false,false,true,true,true,true,true,true,true,true,false,false,false,false,false,false,false,false,false,false,false,false,false,false,false,false,false,false,false,false,false,true,true,true,true,true,true,true,true,true,true,false,false,false,false,false,false,false,false,false,false,true,true,true,true,true,true,true,true,false,false,false,true,true,true,true,true,true,true,true,false,false,false,false,false,false,false,false,false,false,false,false,false,false,false,false,false,false,false,false,false,true,true,true,true,true,true,true,true,true,true,false,false,false,false,false,false,false,false,false,false,true,true,true,true,true,true,true,true,false,false,false,true,true,true,true,true,true,true,true,false,false,false,false,false,false,false,false,false,false,false,false,false,false,false,false,false,false,false,false,false,true,true,true,true,true,true,true,true,true,true,false,false,false,false,false,false,false,false,false,false,false,false,false,false,true,true,false,false,false,false,false,true,true,true,true,true,true,true,true,false,false,false,false,false,false,false,false,false,false,false,false,false,false,false,false,false,false,false,false,false,false,true,true,true,true,true,true,true,true,true,false,false,false,false,false,false,false,false,false,false,false,false,false,false,true,true,false,false,false,false,false,false,false,true,true,true,false,false,false,false,false,false,false,false,false,false,false,false,false,false,false,false,false,false,false,false,false,false,false,false,false,false,true,true,true,true,true,true,true,true,false,false,false,false,false,false,false,false,false,false,false,false,false,false,false,false,false,false,false,false,false,false,false,true,true,true,false,false,false,false,false,false,false,false,false,false,false,false,false,false,false,false,false,false,false,false,false,false,false,false,false,false,false,false,false,false,false,false,false,false,false,false,false,false,false,false,false,false,false,false,false,false,false,false,false,false,false,false,false,false,false,false,false,false,false,false,false,false,false,false,false,false,false,false,false,false,false,false,false,false,false,false,false,false,false,false,false,false,false,false,false,false,false,false,false,false,false,false,false,false,false,false,false,false,false,false,false,false,false,false,false,false,false,false,false,false,false,false,false,false,false,false,false,false,false,false,false,false,false,false,false,false,false,false,false,false,false,false,false,false,false,false,false,false,false,false,false,false,false,false,false,false,false,false,false,false,false,false,false,false,false,false,false,false,false,false,false,false,false,false,false,false,false,false,false,false,false,false,false,false,false,false,false,false,false,false,false,false,false,false,false,false,false,false,false,false,false,false,false,false,false,false,false,false,false,false,false,false,false,false,false,false,false,false,false,false,false,false,false,false,false,false,false,false,false,false,false,false,false,false,false,false,false,false,false,false,false,false,false,false,false,false,false,false,false,false,false,false,false,false,false,false,false,false,false,false,false,false,false,false,false,false,false,false,false,false,false,false,false,false,false,false,false,false,false,false,false,false,false,false,false,false,false,false,false,false,false,false,false,false,false,false,false,false,false,false,false,false,false,false,false,false,false,false,false,false,false,false,false,false,false,false,false,false,false,false,false,false,false,false,false,false,false,false,false,false,false,false,false,false,false,false,false,false,false,false,false,false,false,false,false,false,false,false,false,false,false,false,false,false,false,false,false,false,false,false,false,false,false,false,false,false,false,false,false,false,false,false,false,false,false,false,false,false,false,false,false,false,false,false,false,false,false,false,false,false,false,false,false,false,false,false,false,false,false,false,false,false,false,false,false,false,false,false,false,false,false,false,false,false,false,false,false,false,false,false,false,false,false,false,false,false,false,false,false,false,false,false,false,false,false,false,false,false,false,false,false,false,false,false,false,false,false,false,false,false,false,false,false,false,false,false,false,false,false,false,false,false,false,false,false,false,false,false,false,false,false,false,false,false,false,false,false,false,false,false,false,false,false,false,false,false,false,false,false,false,false,false,false,false,false,false,false,false,false,false,false,false,false,false,false,false,false,false,false,false,false,false,false,false,false,false,false,false,false,false,false,false,false,false,false,false,false,false,false,false,false,false,false,false,false,false,false,false,false,false,false,false,false,false,false,false,false,false,false,false,false,false,false,false,false,false,false,false,false,false,false,false,false,false,false,false,false,false,false,false,false,false,false,false,false,false,false,false,false,false,false,false,false,false,false,false,false,false,false,false,false,false,false,false,false,false,false,false,false,false,false,false,false,false,false,false,false,false,false,false,false,false,false,false,false,false,false,false,false],"visible_tiles":[false,false,false,false,false,false,false,false,false,false,false,false,false,false,false,false,false,false,false,false,false,false,false,false,false,false,false,false,false,false,false,false,false,false,false,false,false,false,false,false,false,false,false,false,false,false,false,false,false,false,false,false,false,false,false,false,false,false,false,false,false,false,false,false,false,false,false,false,false,false,false,false,false,false,false,false,false,false,false,false,false,false,false,false,false,false,false,false,false,false,false,false,false,false,false,false,false,false,false,false,false,false,false,false,false,false,false,false,false,false,false,false,false,false,false,false,false,false,false,false,false,false,false,false,false,false,false,false,false,false,false,false,false,false,false,false,false,false,false,false,false,false,false,false,false,false,false,false,false,false,false,false,false,false,false,false,false,false,false,false,false,false,false,false,false,false,false,false,false,false,false,false,false,false,false,false,false,false,false,false,false,false,false,false,false,false,false,false,false,false,false,false,false,false,false,false,false,false,false,false,false,false,false,false,false,false,false,false,false,false,false,false,false,false,false,false,false,false,false,false,false,false,false,false,false,false,false,false,false,false,false,false,false,false,false,false,false,false,false,false,false,false,false,false,false,false,false,false,false,false,false,false,false,false,false,false,false,false,false,false,false,false,false,false,false,false,false,false,false,false,false,false,false,false,false,false,false,false,false,false,false,false,false,false,false,false,false,false,false,false,false,false,false,false,false,false,false,false,false,false,false,false,false,false,false,false,false,false,false,false,false,false,false,false,false,false,false,false,false,false,false,false,false,false,false,false,false,false,false,false,false,false,false,false,false,false,false,false,false,false,false,false,false,false,false,false,false,false,false,false,false,false,false,false,false,false,false,false,false,false,false,false,false,false,false,false,false,false,false,false,false,false,false,false,false,false,false,false,false,false,false,false,false,false,false,false,false,false,false,false,false,false,false,false,false,false,false,false,false,false,false,false,false,false,false,false,false,false,false,false,false,false,false,false,false,false,false,false,false,false,false,false,false,false,false,false,false,false,false,false,false,false,false,false,false,false,false,false,false,false,false,false,false,false,false,false,false,false,false,false,false,false,false,false,false,false,false,false,false,false,false,false,false,false,false,false,false,false,false,false,false,false,false,false,false,false,false,false,false,false,false,false,false,false,false,false,false,false,false,false,false,false,false,false,false,false,false,false,false,false,false,false,false,false,false,false,false,false,false,false,false,false,false,false,false,false,false,false,false,false,false,false,false,false,false,false,false,false,false,false,false,false,false,false,false,false,false,false,false,false,false,false,false,false,false,false,false,false,false,false,false,false,false,false,false,false,false,false,false,false,false,false,false,false,false,false,false,false,false,false,false,false,false,false,false,false,false,false,false,false,false,false,false,false,false,false,false,false,false,false,false,false,false,false,false,false,false,false,false,false,false,false,false,false,false,false,false,false,false,false,false,false,false,false,false,false,false,false,false,false,false,false,false,false,false,false,false,false,false,false,false,false,false,false,false,false,false,false,false,false,false,false,false,false,false,false,false,false,false,false,false,false,false,false,false,false,false,false,false,false,false,false,false,false,false,false,false,false,false,false,false,false,false,false,false,false,false,false,false,false,false,false,false,false,false,false,false,false,false,false,false,false,false,false,false,false,false,false,false,false,false,false,false,false,false,false,false,false,false,false,false,false,false,false,false,false,false,false,false,false,false,false,false,false,false,false,false,false,false,false,false,false,false,false,false,false,false,false,false,false,false,false,false,false,false,false,false,false,false,false,false,false,false,false,false,false,false,false,false,false,false,false,false,false,false,false,false,false,false,false,false,false,false,false,false,false,false,false,false,false,false,false,false,false,false,false,false,false,false,false,false,false,false,false,false,false,false,false,false,false,false,false,false,false,false,false,false,false,false,false,false,false,false,false,false,false,false,false,false,false,false,false,false,false,false,false,false,false,false,false,false,false,false,false,false,false,false,false,false,false,false,false,false,false,false,false,false,false,false,false,false,false,false,false,false,false,false,false,false,false,false,false,false,false,false,false,false,false,false,false,false,false,false,false,false,false,false,false,false,false,false,false,false,false,false,false,false,false,false,false,false,false,false,false,false,false,false,false,false,false,false,false,false,false,false,false,false,false,false,false,false,false,false,false,false,false,false,false,false,false,false,false,false,false,false,false,false,false,false,false,false,false,false,false,false,false,false,false,false,false,false,false,false,false,false,false,false,false,false,false,false,false,false,false,false,false,false,false,false,false,false,false,false,false,false,false,false,false,false,false,false,false,false,false,false,false,false,false,false,false,false,false,false,false,false,false,false,false,false,false,false,false,false,false,false,false,false,false,false,false,false,false,false,false,false,false,false,false,false,false,false,false,false,false,false,false,false,false,false,false,false,false,false,false,false,false,false,false,false,false,false,false,false,false,false,false,false,false,false,false,false,false,false,false,false,false,false,false,false,false,false,false,false,false,false,false,false,false,false,false,false,false,false,false,false,false,false,false,false,false,false,false,false,false,false,false,false,false,false,false,false,false,false,false,false,false,false,false,false,false,false,false,false,false,false,false,false,false,false,false,false,false,false,false,false,false,false,false,false,false,false,false,false,false,false,false,false,false,false,false,false,false,false,false,false,false,false,false,false,false,false,false,false,false,false,false,false,false,false,false,false,false,false,false,false,false,false,false,false,false,false,false,false,false,false,false,false,false,false,false,false,false,false,false,false,false,false,false,false,false,false,false,false,false,false,false,false,false,false,false,false,false,false,false,false,false,false,false,false,false,false,false,false,false,false,false,false,false,false,false,false,false,false,false,false,false,false,false,false,false,false,false,false,false,false,false,false,false,false,false,false,false,false,false,false,false,false,false,false,false,false,false,false,false,false,false,false,false,false,false,false,false,false,false,false,false,false,false,false,false,false,false,false,false,false,false,false,false,false,false,false,false,false,false,false,false,false,false,false,false,false,false,false,false,false,false,false,false,true,false,false,false,false,false,false,false,false,false,false,false,false,false,false,false,false,false,false,false,false,false,false,false,false,false,false,false,false,false,false,false,false,false,false,false,false,false,false,false,false,false,false,false,false,false,false,false,false,false,false,false,false,false,false,false,false,true,true,true,true,true,true,true,true,true,true,false,false,false,false,false,false,false,false,false,false,false,false,false,false,false,false,false,false,false,false,false,false,false,false,false,false,false,false,false,false,false,false,false,false,false,false,false,false,false,false,false,false,false,false,false,false,false,false,false,false,true,true,true,true,true,true,true,true,true,true,true,true,true,true,true,false,false,false,false,false,false,false,false,false,false,false,false,false,false,false,false,false,false,false,false,false,false,false,false,false,false,false,false,false,false,false,false,false,false,false,false,false,false,false,false,false,false,false,false,false,true,true,true,true,true,true,true,true,true,true,true,true,true,true,true,false,false,false,false,false,false,false,false,false,false,false,false,false,false,false,false,false,false,false,false,false,false,false,false,false,false,false,false,false,false,false,false,false,false,false,false,false,false,false,false,false,false,false,false,false,true,true,true,true,true,true,true,true,true,true,true,true,true,true,true,false,false,false,false,false,false,false,false,false,false,false,false,false,false,false,false,false,false,false,false,false,false,false,false,false,false,false,false,false,false,false,false,false,false,false,false,false,false,false,false,false,false,false,false,false,true,true,true,true,true,true,true,true,true,true,false,false,false,false,false,false,false,false,false,false,false,false,false,false,false,false,false,false,false,false,false,false,false,false,false,false,false,false,false,false,false,false,false,false,false,false,false,false,false,false,false,false,false,false,false,false,false,false,false,false,true,true,true,true,true,true,true,true,true,true,false,false,false,false,false,false,false,false,false,false,false,false,false,false,false,false,false,false,false,false,false,false,false,false,false,false,false,false,false,false,false,false,false,false,false,false,false,false,false,false,false,false,false,false,false,false,false,false,false,false,true,true,true,true,true,true,true,true,true,true,false,false,false,false,false,false,false,false,false,false,false,false,false,false,false,false,false,false,false,false,false,false,false,false,false,false,false,false,false,false,false,false,false,false,false,false,false,false,false,false,false,false,false,false,false,false,false,false,false,false,true,true,true,true,true,true,true,true,true,true,false,false,false,false,false,false,false,false,false,false,false,false,false,false,false,false,false,false,false,false,false,false,false,false,false,false,false,false,false,false,false,false,false,false,false,false,false,false,false,false,false,false,false,false,false,false,false,false,false,false,true,true,true,true,true,true,true,true,true,true,false,false,false,false,false,false,false,false,false,false,false,false,false,false,false,false,false,false,false,false,false,false,false,false,false,false,false,false,false,false,false,false,false,false,false,false,false,false,false,false,false,false,false,false,false,false,false,false,false,false,false,true,true,true,true,true,true,true,true,true,false,false,false,false,false,false,false,false,false,false,false,false,false,false,false,false,false,false,false,false,false,false,false,false,false,false,false,false,false,false,false,false,false,false,false,false,false,false,false,false,false,false,false,false,false,false,false,false,false,false,false,false,false,true,true,true,true,true,true,true,false,false,false,false,false,false,false,false,false,false,false,false,false,false,false,false,false,false,false,false,false,false,false,false,false,false,false,false,false,false,false,false,false,false,false,false,false,false,false,false,false,false,false,false,false,false,false,false,false,false,false,false,false,false,false,false,false,false,false,false,false,false,false,false,false,false,false,false,false,false,false,false,false,false,false,false,false,false,false,false,false,false,false,false,false,false,false,false,false,false,false,false,false,false,false,false,false,false,false,false,false,false,false,false,false,false,false,false,false,false,false,false,false,false,false,false,false,false,false,false,false,false,false,false,false,false,false,false,false,false,false,false,false,false,false,false,false,false,false,false,false,false,false,false,false,false,false,false,false,false,false,false,false,false,false,false,false,false,false,false,false,false,false,false,false,false,false,false,false,false,false,false,false,false,false,false,false,false,false,false,false,false,false,false,false,false,false,false,false,false,false,false,false,false,false,false,false,false,false,false,false,false,false,false,false,false,false,false,false,false,false,false,false,false,false,false,false,false,false,false,false,false,false,false,false,false,false,false,false,false,false,false,false,false,false,false,false,false,false,false,false,false,false,false,false,false,false,false,false,false,false,false,false,false,false,false,false,false,false,false,false,false,false,false,false,false,false,false,false,false,false,false,false,false,false,false,false,false,false,false,false,false,false,false,false,false,false,false,false,false,false,false,false,false,false,false,false,false,false,false,false,false,false,false,false,false,false,false,false,false,false,false,false,false,false,false,false,false,false,false,false,false,false,false,false,false,false,false,false,false,false,false,false,false,false,false,false,false,false,false,false,false,false,false,false,false,false,false,false,false,false,false,false,false,false,false,false,false,false,false,false,false,false,false,false,false,false,false,false,false,false,false,false,false,false,false,false,false,false,false,false,false,false,false,false,false,false,false,false,false,false,false,false,false,false,false,false,false,false,false,false,false,false,false,false,false,false,false,false,false,false,false,false,false,false,false,false,false,false,false,false,false,false,false,false,false,false,false,false,false,false,false,false,false,false,false,false,false,false,false,false,false,false,false,false,false,false,false,false,false,false,false,false,false,false,false,false,false,false,false,false,false,false,false,false,false,false,false,false,false,false,false,false,false,false,false,false,false,false,false,false,false,false,false,false,false,false,false,false,false,false,false,false,false,false,false,false,false,false,false,false,false,false,false,false,false,false,false,false,false,false,false,false,false,false,false,false,false,false,false,false,false,false,false,false,false,false,false,false,false,false,false,false,false,false,false,false,false,false,false,false,false,false,false,false,false,false,false,false,false,false,false,false,false,false,false,false,false,false,false,false,false,false,false,false,false,false,false,false,false,false,false,false,false,false,false,false,false,false,false,false,false,false,false,false,false,false,false,false,false,false,false,false,false,false,false,false,false,false,false,false,false,false,false,false,false,false,false,false,false,false,false,false,false,false,false,false,false,false,false,false,false,false,false,false,false,false,false,false,false,false,false,false,false,false],"blocked":[true,true,true,true,true,true,true,true,true,true,true,true,true,true,true,true,true,true,true,true,true,true,true,true,true,true,true,true,true,true,true,true,true,true,true,true,true,true,true,true,true,true,true,true,true,true,true,true,true,true,true,true,true,true,true,true,true,true,true,true,true,true,true,true,true,true,true,true,true,true,true,true,true,true,true,true,true,true,false,false,false,false,false,false,true,true,true,true,true,true,true,true,true,true,true,true,true,true,true,true,true,true,true,true,true,true,true,true,true,true,true,true,true,true,true,true,true,true,true,true,true,true,true,true,true,true,true,false,false,true,false,false,false,true,true,true,true,true,false,false,false,false,false,false,true,true,true,true,true,true,true,true,true,true,true,true,true,true,true,true,true,true,true,true,true,true,true,true,true,true,true,true,true,true,true,true,true,true,true,true,true,true,true,true,true,true,true,false,false,false,false,false,false,true,true,true,true,true,false,false,false,false,false,false,false,true,true,true,true,true,true,true,true,true,true,true,true,true,true,true,true,true,true,true,true,true,true,true,true,true,true,true,true,true,true,true,true,true,true,true,true,true,true,true,true,true,true,false,false,false,false,false,false,true,true,true,true,true,false,false,false,false,false,false,false,true,true,true,true,true,true,true,true,true,true,true,true,true,true,true,true,true,true,true,true,true,true,true,true,true,true,true,true,true,true,true,true,true,true,true,true,true,true,true,true,true,true,false,false,false,false,false,false,true,true,true,true,true,false,false,false,false,false,false,false,true,true,true,true,true,true,true,true,true,true,true,true,true,true,true,true,true,true,true,true,true,true,true,true,true,true,true,true,true,true,true,true,true,true,true,true,true,true,true,true,true,true,false,false,false,false,false,false,true,true,true,true,true,false,false,false,false,false,false,false,true,true,true,true,true,true,true,true,true,true,true,true,true,true,true,true,true,true,true,true,true,false,false,false,false,false,false,false,false,true,true,true,true,true,true,true,true,true,true,true,true,true,false,false,false,false,false,false,true,true,true,true,true,false,false,false,false,false,false,false,true,true,true,true,true,true,true,true,true,true,true,true,true,true,true,true,true,true,true,true,true,false,false,false,false,false,false,false,false,true,true,true,true,true,true,true,true,true,true,true,true,true,false,false,false,false,false,false,true,true,true,true,true,true,false,true,true,true,true,false,true,true,true,true,true,true,true,true,true,true,true,true,true,true,true,true,true,true,true,true,true,false,false,false,false,false,false,false,false,true,true,true,true,true,true,true,true,true,true,true,true,true,true,true,false,false,false,false,false,false,false,false,false,false,false,false,false,false,false,false,false,false,false,false,false,false,false,false,false,false,false,false,false,false,false,false,false,false,false,false,false,false,false,false,false,false,false,false,false,true,true,true,true,true,true,true,true,true,true,true,true,true,true,true,true,true,true,true,false,false,false,false,false,false,false,false,true,true,true,false,true,true,true,true,true,true,true,true,true,true,true,false,false,false,false,false,false,false,false,false,true,false,false,false,false,false,false,false,false,true,true,true,true,true,true,true,true,true,true,true,true,true,true,true,true,true,true,true,false,false,false,false,false,false,false,false,true,false,false,false,false,false,false,false,true,true,true,true,true,true,true,false,false,false,false,false,false,false,false,false,true,false,false,false,false,false,false,false,false,true,true,true,true,true,true,true,true,true,true,true,true,true,true,true,true,true,true,true,false,false,false,false,false,false,false,false,true,false,false,false,false,false,false,false,true,true,true,true,true,true,true,false,false,false,false,false,false,false,false,false,true,false,false,false,false,false,false,false,false,true,true,true,true,true,true,true,true,true,true,true,true,true,true,false,false,false,false,false,false,false,false,false,false,false,false,false,false,false,false,false,false,false,false,false,true,true,true,true,true,true,true,false,false,false,false,false,false,false,false,false,false,false,false,false,false,false,false,false,false,true,true,true,true,true,true,true,true,true,true,true,true,true,true,false,true,true,true,true,false,false,false,false,false,false,false,false,true,true,false,false,false,false,false,false,true,true,true,true,true,true,true,false,false,false,false,false,false,false,false,false,true,false,false,false,false,false,false,false,false,true,true,true,true,true,true,true,true,true,true,true,true,true,true,false,true,true,true,true,false,false,false,false,false,false,false,false,true,false,false,false,false,false,false,false,true,true,true,true,true,true,true,false,false,false,false,false,false,false,false,false,true,true,true,true,false,true,true,true,true,true,true,true,true,true,true,true,true,true,true,true,true,true,true,false,true,true,true,true,false,false,false,false,false,false,false,false,true,false,false,false,false,false,false,false,true,true,true,true,true,true,true,false,false,false,false,false,false,false,false,false,true,true,true,true,false,true,true,true,true,true,true,true,true,true,true,true,true,true,true,true,true,true,true,false,true,true,true,true,true,true,true,false,true,true,false,true,true,false,false,false,false,false,false,false,true,true,true,true,true,true,true,false,false,false,false,false,false,false,false,false,true,true,true,true,false,true,true,true,true,true,true,true,true,true,true,true,true,true,true,true,true,true,true,false,true,true,true,true,true,true,true,false,true,true,false,true,true,true,true,true,true,true,true,true,true,true,true,true,true,true,true,true,true,true,false,true,true,true,true,true,true,true,true,true,false,true,true,true,true,true,true,true,true,true,true,true,true,true,true,true,true,true,true,false,true,true,true,true,true,true,true,false,true,true,false,true,true,true,true,true,true,true,true,true,true,true,true,true,true,true,true,true,true,true,false,true,true,true,true,true,true,true,true,true,false,true,true,true,true,true,true,true,true,true,true,true,true,true,true,true,true,true,true,false,true,true,true,true,true,true,true,false,true,true,false,true,true,true,true,true,true,true,true,true,true,true,true,true,true,true,true,true,true,true,false,true,true,true,true,true,true,true,true,true,false,true,true,true,true,true,true,true,true,true,true,true,true,true,true,true,true,false,false,false,false,false,false,false,true,true,true,false,true,true,false,true,true,true,true,true,true,true,true,true,true,true,true,true,true,true,true,false,false,false,false,false,false,true,true,true,true,true,false,false,false,false,false,false,true,true,true,true,true,true,true,true,true,true,true,true,true,false,false,false,false,false,false,false,true,true,true,false,true,true,false,true,true,true,true,true,true,true,true,true,true,true,true,true,true,true,true,false,false,false,false,false,false,true,true,true,true,true,false,false,false,false,false,false,true,true,true,true,true,true,true,true,true,true,true,true,true,false,false,false,false,false,false,false,true,true,true,false,false,false,false,false,false,false,false,true,true,true,true,true,true,true,true,true,true,true,true,false,false,false,false,false,false,true,true,true,true,true,false,false,false,false,false,false,true,true,true,true,true,true,true,true,true,true,true,true,true,false,false,false,false,false,false,false,true,true,true,false,false,false,false,false,false,false,false,false,false,false,false,false,false,false,false,false,false,false,false,false,false,false,false,false,false,true,true,true,true,true,false,false,false,false,false,false,true,true,true,true,true,true,true,true,true,true,true,true,true,false,false,false,false,false,false,false,true,true,true,false,false,false,false,false,false,false,false,true,true,true,true,true,true,true,true,true,true,true,true,false,false,false,false,false,false,true,true,true,true,true,false,false,false,false,false,false,true,true,true,true,true,true,true,true,true,true,true,true,true,false,false,false,false,false,false,false,true,true,true,false,false,false,false,false,false,false,false,true,true,true,true,true,true,true,true,true,true,true,true,false,false,false,false,false,false,true,true,true,true,true,false,false,false,false,false,false,true,true,true,true,true,true,true,true,true,true,true,true,true,false,false,false,false,false,false,false,true,true,true,false,false,false,false,false,false,false,false,true,true,true,true,true,true,true,true,true,true,true,true,false,false,false,false,false,false,true,true,true,true,true,false,false,false,false,false,false,true,true,true,true,true,true,true,true,true,true,true,true,true,false,false,false,false,false,false,false,true,true,true,false,false,false,false,false,false,false,false,true,true,true,true,true,true,true,true,true,true,true,true,false,false,false,false,false,false,true,true,true,true,true,false,false,false,false,false,false,true,true,true,true,true,true,true,true,true,true,true,true,true,true,true,false,true,true,true,true,true,true,true,false,false,false,false,false,false,false,false,true,true,true,true,true,true,true,true,true,true,true,true,true,true,true,false,true,true,true,true,true,true,true,false,false,false,false,false,false,true,true,true,true,true,true,true,true,true,true,true,true,true,false,false,false,false,false,false,false,true,true,true,false,false,false,false,false,false,false,false,true,true,true,false,false,false,false,false,false,false,false,true,true,true,true,false,true,true,true,true,true,true,true,true,true,false,true,true,true,true,true,true,true,true,true,true,true,true,true,true,true,true,false,false,false,false,false,false,false,true,true,true,false,false,false,false,false,false,false,false,true,true,true,false,false,false,false,false,false,false,false,true,true,true,true,false,true,true,true,true,true,true,true,true,true,false,true,true,true,true,true,true,true,true,true,true,true,true,true,true,true,true,false,false,false,false,false,false,false,true,true,true,false,true,true,true,true,true,true,true,true,true,true,false,false,false,false,false,false,false,false,true,true,true,true,false,true,true,true,true,true,true,true,true,true,false,true,true,true,true,true,true,true,true,true,true,true,true,true,true,true,true,false,false,false,false,false,false,false,false,false,false,false,false,false,false,false,false,false,false,false,false,false,false,false,false,false,false,false,false,false,false,false,false,false,false,false,false,false,false,false,false,false,false,false,false,true,true,true,true,true,true,true,true,true,true,true,true,true,true,true,true,false,false,false,false,false,false,false,true,true,true,true,true,true,true,true,true,true,true,true,true,true,false,false,false,false,false,false,false,false,true,true,true,true,true,true,true,true,true,true,true,true,true,true,true,true,true,true,true,true,true,true,true,true,true,true,true,true,true,true,true,false,false,false,false,false,false,false,true,true,true,true,true,true,true,true,true,true,true,true,true,true,false,false,false,false,false,false,false,false,true,true,true,true,true,true,true,true,true,true,true,true,true,true,true,true,true,true,true,true,true,true,true,true,true,true,true,true,true,true,true,false,false,false,false,false,false,false,true,true,true,true,true,true,true,true,true,true,true,true,true,true,false,false,false,false,false,false,false,false,true,true,true,true,true,true,true,true,true,true,true,true,true,true,true,true,true,true,true,true,true,true,true,true,true,true,true,true,true,true,true,false,false,false,false,false,false,false,true,true,true,true,true,true,true,true,true,true,true,true,true,true,false,false,false,false,false,false,false,false,true,true,true,true,true,true,true,true,true,true,true,true,true,true,true,true,true,true,true,true,true,true,true,true,true,true,true,true,true,true,true,true,true,true,true,true,true,true,true,true,true,true,true,true,true,true,true,true,true,true,true,true,true,true,true,true,true,true,true,true,true,true,true,true,true,true,true,true,true,true,true,true,true,true,true,true,true,true,true,true,true,true,true,true,true,true,true,true,true,true,true,true,true,true,true,true,true,true,true,true,true,true,true,true,true,true,true,true,true,true,true,true,true,true,true,true,true,true,true,true,true,true,true,true,true,true,true,true,true,true,true,true,true,true,true,true,true,true,true,true,true,true,true,true,true,true,true,true,true,true,true,true,true,true,true,true,true,true,true,true,true,true,true,true,true,true,true,true,true,true,true,true,true,true,true,true,true,true,true,true,true,true,true,true,true,true,true,true,true,true,true,true,true,true,true,true,true,true,true,true,true,true,true,true,true,true,true,true,true,true,true,true,true,true,true,true,true,true,true,true,true,true,true,true,true,true,true,true,true,true,true,true,true,true,true,true,true,true,true,true,true,true,true,true,true,true,true,true,true,true,true,true,true,true,true,true,true,true,true,true,true,true,true,true,true,true,true,true,true,true,true,true,true,true,true,true,true,true,true,true,true,true,true,true,true,true,true,true,true,true,true,true,true,true,true,true,true,true,true,true,true,true,true,true,true,true,true,true,true,true,true,true,true,true,true,true,true,true,true,true,true,true,true,true,true],"depth":1,"bloodstains":[1461,1522]}}]}][{"marker":[0],"components":[null]},{"marker":[1],"components":[null]},{"marker":[2],"components":[null]},{"marker":[3],"components":[null]},{"marker":[4],"components":[null]},{"marker":[5],"components":[null]},{"marker":[6],"components":[null]},{"marker":[8],"components":[null]},{"marker":[9],"components":[null]},{"marker":[10],"components":[null]},{"marker":[11],"components":[null]},{"marker":[12],"components":[null]},{"marker":[13],"components":[null]},{"marker":[14],"components":[null]},{"marker":[15],"components":[null]},{"marker":[16],"components":[null]}][{"marker":[0],"components":[null]},{"marker":[1],"components":[null]},{"marker":[2],"components":[null]},{"marker":[3],"components":[null]},{"marker":[4],"components":[null]},{"marker":[5],"components":[null]},{"marker":[6],"components":[null]},{"marker":[8],"components":[null]},{"marker":[9],"components":[null]},{"marker":[10],"components":[null]},{"marker":[11],"components":[null]},{"marker":[12],"components":[null]},{"marker":[13],"components":[null]},{"marker":[14],"components":[null]},{"marker":[15],"components":[null]},{"marker":[16],"components":[null]}][{"marker":[0],"components":[null]},{"marker":[1],"components":[null]},{"marker":[2],"components":[null]},{"marker":[3],"components":[null]},{"marker":[4],"components":[null]},{"marker":[5],"components":[null]},{"marker":[6],"components":[null]},{"marker":[8],"components":[null]},{"marker":[9],"components":[null]},{"marker":[10],"components":[null]},{"marker":[11],"components":[null]},{"marker":[12],"components":[null]},{"marker":[13],"components":[null]},{"marker":[14],"components":[null]},{"marker":[15],"components":[null]},{"marker":[16],"components":[null]}][{"marker":[0],"components":[null]},{"marker":[1],"components":[null]},{"marker":[2],"components":[null]},{"marker":[3],"components":[null]},{"marker":[4],"components":[null]},{"marker":[5],"components":[null]},{"marker":[6],"components":[null]},{"marker":[8],"components":[null]},{"marker":[9],"components":[null]},{"marker":[10],"components":[null]},{"marker":[11],"components":[null]},{"marker":[12],"components":[null]},{"marker":[13],"components":[null]},{"marker":[14],"components":[null]},{"marker":[15],"components":[null]},{"marker":[16],"components":[null]}][{"marker":[0],"components":[null]},{"marker":[1],"components":[null]},{"marker":[2],"components":[null]},{"marker":[3],"components":[null]},{"marker":[4],"components":[null]},{"marker":[5],"components":[null]},{"marker":[6],"components":[null]},{"marker":[8],"components":[null]},{"marker":[9],"components":[null]},{"marker":[10],"components":[null]},{"marker":[11],"components":[null]},{"marker":[12],"components":[null]},{"marker":[13],"components":[null]},{"marker":[14],"components":[null]},{"marker":[15],"components":[null]},{"marker":[16],"components":[null]}][{"marker":[0],"components":[{"last_second":1621962618131,"last_10sec":0,"last_minute":0,"last_10min":0,"last_hour":0,"min":53,"hour":12,"day":1,"season":1,"year":1}]},{"marker":[1],"components":[null]},{"marker":[2],"components":[null]},{"marker":[3],"components":[null]},{"marker":[4],"components":[null]},{"marker":[5],"components":[null]},{"marker":[6],"components":[null]},{"marker":[8],"components":[null]},{"marker":[9],"components":[null]},{"marker":[10],"components":[null]},{"marker":[11],"components":[null]},{"marker":[12],"components":[null]},{"marker":[13],"components":[null]},{"marker":[14],"components":[null]},{"marker":[15],"components":[null]},{"marker":[16],"components":[null]}][{"marker":[0],"components":[null]},{"marker":[1],"components":[null]},{"marker":[2],"components":[null]},{"marker":[3],"components":[null]},{"marker":[4],"components":[null]},{"marker":[5],"components":[null]},{"marker":[6],"components":[null]},{"marker":[8],"components":[null]},{"marker":[9],"components":[null]},{"marker":[10],"components":[null]},{"marker":[11],"components":[null]},{"marker":[12],"components":[null]},{"marker":[13],"components":[null]},{"marker":[14],"components":[null]},{"marker":[15],"components":[null]},{"marker":[16],"components":[null]}][{"marker":[0],"components":[{"state":"Normal","duration":167}]},{"marker":[1],"components":[null]},{"marker":[2],"components":[null]},{"marker":[3],"components":[null]},{"marker":[4],"components":[null]},{"marker":[5],"components":[null]},{"marker":[6],"components":[null]},{"marker":[8],"components":[null]},{"marker":[9],"components":[null]},{"marker":[10],"components":[null]},{"marker":[11],"components":[null]},{"marker":[12],"components":[null]},{"marker":[13],"components":[null]},{"marker":[14],"components":[null]},{"marker":[15],"components":[null]},{"marker":[16],"components":[null]}][{"marker":[0],"components":[null]},{"marker":[1],"components":[null]},{"marker":[2],"components":[{}]},{"marker":[3],"components":[null]},{"marker":[4],"components":[null]},{"marker":[5],"components":[null]},{"marker":[6],"components":[null]},{"marker":[8],"components":[null]},{"marker":[9],"components":[null]},{"marker":[10],"components":[null]},{"marker":[11],"components":[null]},{"marker":[12],"components":[null]},{"marker":[13],"components":[null]},{"marker":[14],"components":[null]},{"marker":[15],"components":[null]},{"marker":[16],"components":[null]}][{"marker":[0],"components":[null]},{"marker":[1],"components":[null]},{"marker":[2],"components":[null]},{"marker":[3],"components":[null]},{"marker":[4],"components":[null]},{"marker":[5],"components":[null]},{"marker":[6],"components":[null]},{"marker":[8],"components":[null]},{"marker":[9],"components":[null]},{"marker":[10],"components":[null]},{"marker":[11],"components":[null]},{"marker":[12],"components":[null]},{"marker":[13],"components":[null]},{"marker":[14],"components":[null]},{"marker":[15],"components":[null]},{"marker":[16],"components":[null]}][{"marker":[0],"components":[null]},{"marker":[1],"components":[{}]},{"marker":[2],"components":[null]},{"marker":[3],"components":[{}]},{"marker":[4],"components":[null]},{"marker":[5],"components":[{}]},{"marker":[6],"components":[{}]},{"marker":[8],"components":[{}]},{"marker":[9],"components":[null]},{"marker":[10],"components":[{}]},{"marker":[11],"components":[null]},{"marker":[12],"components":[{}]},{"marker":[13],"components":[{}]},{"marker":[14],"components":[null]},{"marker":[15],"components":[{}]},{"marker":[16],"components":[null]}]